src/register_file.sv
module register_file (
    input clk,
    input rst_n,

    input  [ 4:0] rs1_addr,
    input  [ 4:0] rs2_addr,
    output [31:0] rs1_data,
    output [31:0] rs2_data,

    input        we,
    input [ 4:0] rd_addr,
    input [31:0] rd_data
);

  reg [31:0] registers[31:0];
  reg [ 2:0] flags    [ 2:0];

  assign rs1_data = (rs1_addr == 0) ? 32'b0 : registers[rs1_addr];
  assign rs2_data = (rs2_addr == 0) ? 32'b0 : registers[rs2_addr];

  always @(posedge clk or negedge rst_n) begin
    if (!rst_n) begin
      integer i;
      for (i = 0; i < 32; i = i + 1) begin
        registers[i] <= 32'b0;
      end
    end else if (we && rd_addr != 0) begin
      registers[rd_addr] <= rd_data;
    end
  end

endmodule

src/decoder.sv
module decoder (
    input [31:0] instr,

    output reg [3:0] alu_ops,  // add, sub, xor, or, and, sll, srl, sra, slt, sltu

    output reg reg_write,  // 1 for R, I. 0 for S, B

    output reg       mem_read,   // 1 for LB/LH/LW
    output reg       mem_write,  // 1 for SB/SH/SW
    output reg [1:0] mem_width,  // 00 byte, 01 half, 10 word

    output reg       is_branch,
    output reg [2:0] branch_type,  // BEQ, BNE, BLT, BGE, BLTU, BGEU
    output reg       is_jump,
    output reg       is_jalr,
    output reg       is_lui,
    output reg       is_i_type,

    output     [4:0] rs1,
    output     [4:0] rs2,
    output reg       rs1_used,
    output reg       rs2_used,

    output [4:0] rd,

    output reg [31:0] imm
);

  wire [4:0] opcode = instr[6:2];
  wire [2:0] funct3 = instr[14:12];
  wire [6:0] funct7 = instr[31:25];

  localparam R_TYPE = 5'b01100;
  localparam I_TYPE = 5'b00100;
  localparam LUI = 5'b01101;
  localparam LOAD = 5'b00000;
  localparam STORE = 5'b01000;
  localparam BRANCH = 5'b11000;
  localparam JAL = 5'b11011;
  localparam JALR = 5'b11001;

  assign rs1 = instr[19:15];
  assign rs2 = instr[24:20];

  assign rd  = instr[11:7];

  always @(*) begin
    is_lui = 0;
    is_i_type = 0;
    case (opcode)
      R_TYPE: begin
        if (funct7 != 7'b0000001) begin
          case (funct3)
            3'b000: alu_ops = (funct7 !== 7'b0100000) ? 4'b0000 : 4'b0001;  // ADD / SUB
            3'b100: alu_ops = 4'b0010;  // XOR
            3'b110: alu_ops = 4'b0011;  // OR
            3'b111: alu_ops = 4'b0100;  // AND
            3'b001: alu_ops = 4'b0101;  // SLL
            3'b101: alu_ops = (funct7 !== 7'b0100000) ? 4'b0111 : 4'b1000;  // SRL : SRA
            3'b010: alu_ops = 4'b1001;  // SLT
            3'b011: alu_ops = 4'b1011;  // SLTU
          endcase
        end else begin
          case (funct3)
            3'b000:  alu_ops = 4'b1100;  // MUL
            3'b100:  alu_ops = 4'b1101;  // DIV
            default: alu_ops = 4'b0000;  // REST NOT DEFINED !! TODO
          endcase
        end

        rs1_used = 1;
        rs2_used = 1;
      end

      I_TYPE: begin
        case (funct3)
          3'b000: alu_ops = 4'b0000;
          3'b100: alu_ops = 4'b0010;
          3'b110: alu_ops = 4'b0011;
          3'b111: alu_ops = 4'b0100;
          3'b101: begin
            if (imm[11:5] == 7'b0000000) alu_ops = 4'b0101;
            else if (imm[11:5] == 7'b0100000) alu_ops = 4'b0111;
          end
          3'b010: alu_ops = 4'b1001;
          3'b011: alu_ops = 4'b1011;
        endcase

        is_i_type = 1;
      end

      LUI: begin
        is_lui = 1;
        imm = instr[31:20];
        reg_write = 1;
      end
      default: is_i_type = 0;
    endcase
  end

endmodule

src/alu.sv
module alu (
    input clk,
    input is_lui,
    input is_i_type,
    input [3:0] alu_ops,
    input [31:0] rs1_data,
    input [31:0] rs2_data,
    input [31:0] imm,
    output reg [31:0] rd_data
);

  always @* begin
    rd_data = 32'b0;

    if (is_lui) begin
      rd_data = imm << 12;
    end else if (is_i_type) begin
      rd_data = rs1_data + imm;
    end else begin
      case (alu_ops)
        4'b0000: rd_data = rs1_data + rs2_data;
        4'b0001: rd_data = rs1_data - rs2_data;
        default: rd_data = 32'b0;
      endcase
    end
  end

endmodule

src/instruction_memory.sv
module instruction_memory (
    input  wire [31:0] addr,
    output reg  [31:0] instr_out
);
  reg [31:0] memory[0:1023];
  integer i;
  integer file;
  integer status;
  reg continue_reading;

  initial begin
    for (i = 0; i < 1024; i = i + 1) begin
      memory[i] = 32'h0;
    end

    file = $fopen("program", "rb");
    if (file == 0) begin
      $display("Error: Failed to open file");
      $finish;
    end

    i = 0;
    continue_reading = 1;

    while (continue_reading && i < 1024) begin
      status = $fgetc(file);
      if (status != -1) begin
        memory[i][31:24] = status;

        status = $fgetc(file);
        if (status != -1) begin
          memory[i][23:16] = status;

          status = $fgetc(file);
          if (status != -1) begin
            memory[i][15:8] = status;

            status = $fgetc(file);
            if (status != -1) begin
              memory[i][7:0] = status;
            end else begin
              memory[i][7:0]   = 8'h00;
              continue_reading = 0;
            end
          end else begin
            memory[i][15:0]  = 16'h0000;
            continue_reading = 0;
          end
        end else begin
          memory[i][23:0]  = 24'h000000;
          continue_reading = 0;
        end
        i = i + 1;
      end else begin
        continue_reading = 0;
      end
    end

    $fclose(file);

`ifdef DEBUG
    $display("Loaded %0d 32-bit instructions", i);
    $display("Memory initialization complete");
`endif
  end

  always @(*) begin
    instr_out = memory[addr>>2];
  end

endmodule

src/program_counter.sv
module program_counter (
    input wire clk,
    input wire rst,
    input wire enable,
    input wire load,
    input wire [31:0] addr,
    output reg [31:0] pc
);

  always @(posedge clk or posedge rst) begin
    if (rst) begin
      pc <= 32'b0;
    end else if (enable) begin
      if (load) begin
        pc <= addr;
      end else begin
        pc <= pc + 32'd4;
      end
    end
  end

endmodule

src/top.sv
module top (
    input wire clk
);

  // instr fetch signals
  wire [31:0] instr;
  wire pc_enable;
  wire pc_load;
  wire [31:0] load_addr;
  wire [31:0] pc_out;

  // control signals from decoder
  wire [3:0] alu_ops;
  wire reg_write;
  wire mem_read;
  wire mem_write;
  wire [1:0] mem_width;
  wire is_branch;
  wire [2:0] branch_type;
  wire is_jump;
  wire is_jalr;
  wire is_i_type;
  wire [4:0] rs1;
  wire [4:0] rs2;
  wire [31:0] rs1_data;
  wire [31:0] rs2_data;
  wire [4:0] rd;
  wire [31:0] rd_data;
  wire [31:0] imm;
  wire is_lui;

  // pc control
  assign pc_enable = 1'b1;
  assign pc_load   = 1'b0;  // modify this based on branch/jump results
  assign load_addr = 32'b0;  // set this to branch/jump target

  // reset logic
  reg rst;
  initial begin
    rst = 1'b1;
    #10 rst = 1'b0;
  end

  program_counter pc_inst (
      .clk(clk),
      .rst(rst),
      .enable(pc_enable),
      .load(pc_load),
      .addr(load_addr),
      .pc(pc_out)
  );

  instruction_memory instr_mem (
      .addr(pc_out),
      .instr_out(instr)
  );

  alu alu_inst (
    .clk(clk),
    .is_lui(is_lui),
    .imm(imm),
    .rd_data(rd_data),
    .is_i_type(is_i_type),
    .rs1_data(rs1_data),
    .rs2_data(rs2_data),
    .alu_ops(alu_ops)
  );

  decoder decoder_inst (
      .instr(instr),
      .alu_ops(alu_ops),
      .reg_write(reg_write),
      .mem_read(mem_read),
      .mem_write(mem_write),
      .mem_width(mem_width),
      .is_branch(is_branch),
      .branch_type(branch_type),
      .is_jump(is_jump),
      .is_jalr(is_jalr),
      .rs1(rs1),
      .rs2(rs2),
      .rd(rd),
      .imm(imm),
      .is_lui(is_lui),
      .is_i_type(is_i_type)
  );

  register_file regfile_inst (
    .clk(clk),
    .rs1_addr(rs1),
    .rs2_addr(rs2),
    .rs1_data(rs1_data),
    .rs2_data(rs2_data),

    .we(reg_write),
    .rd_addr(rd),
    .rd_data(rd_data)
  );

endmodule

tb/top_tb.sv
module top_tb;

    reg clk;
    wire [31:0] pc_out;
    wire [31:0] instr;
    
    top dut (
        .clk(clk)
    );
    
    initial begin
        clk = 0;
        forever #5 clk = ~clk;
    end
    
    initial begin
        $dumpfile("top_tb.vcd");
        $dumpvars(0, top_tb);
        
        #15;
        
        #50;
        
        $display("Simulation completed successfully");
        $finish;
    end
    
    always @(posedge clk) begin
        $display("Time=%0t pc=%h instr=%h", 
                 $time, dut.pc_out, dut.instr);
    end
    
    initial begin
        #1;
        assert(dut.rst === 1'b1) 
        else $error("Reset not active at start");
        
        #11;
        assert(dut.rst === 1'b0) 
        else $error("Reset not deasserted after 10 time units");

        assert(dut.alu_ops === 4'b0000)
        else $error("alu_ops not 0000 for ADD");
        
        @(posedge clk);
        if (dut.pc_out !== 32'h0)
            $error("PC not reset to 0");
            
        @(posedge clk);
        if (dut.pc_out !== 32'h1)
            $error("PC not incrementing");
    end

endmodule

top_tb.vcd
$date
	Fri Feb  7 11:39:08 2025
$end
$version
	Icarus Verilog
$end
$timescale
	1s
$end
$scope module top_tb $end
$var reg 1 ! clk $end
$scope module dut $end
$var wire 1 ! clk $end
$var wire 32 " load_addr [31:0] $end
$var wire 1 # pc_enable $end
$var wire 1 $ pc_load $end
$var wire 32 % rs2_data [31:0] $end
$var wire 5 & rs2 [4:0] $end
$var wire 32 ' rs1_data [31:0] $end
$var wire 5 ( rs1 [4:0] $end
$var wire 1 ) reg_write $end
$var wire 32 * rd_data [31:0] $end
$var wire 5 + rd [4:0] $end
$var wire 32 , pc_out [31:0] $end
$var wire 1 - mem_write $end
$var wire 2 . mem_width [1:0] $end
$var wire 1 / mem_read $end
$var wire 1 0 is_lui $end
$var wire 1 1 is_jump $end
$var wire 1 2 is_jalr $end
$var wire 1 3 is_i_type $end
$var wire 1 4 is_branch $end
$var wire 32 5 instr [31:0] $end
$var wire 32 6 imm [31:0] $end
$var wire 3 7 branch_type [2:0] $end
$var wire 4 8 alu_ops [3:0] $end
$var reg 1 9 rst $end
$scope module alu_inst $end
$var wire 1 ! clk $end
$var wire 32 : rs2_data [31:0] $end
$var wire 32 ; rs1_data [31:0] $end
$var wire 1 0 is_lui $end
$var wire 1 3 is_i_type $end
$var wire 32 < imm [31:0] $end
$var wire 4 = alu_ops [3:0] $end
$var reg 32 > rd_data [31:0] $end
$upscope $end
$scope module decoder_inst $end
$var wire 5 ? rs2 [4:0] $end
$var wire 5 @ rs1 [4:0] $end
$var wire 5 A rd [4:0] $end
$var wire 5 B opcode [4:0] $end
$var wire 32 C instr [31:0] $end
$var wire 7 D funct7 [6:0] $end
$var wire 3 E funct3 [2:0] $end
$var parameter 5 F BRANCH $end
$var parameter 5 G I_TYPE $end
$var parameter 5 H JAL $end
$var parameter 5 I JALR $end
$var parameter 5 J LOAD $end
$var parameter 5 K LUI $end
$var parameter 5 L R_TYPE $end
$var parameter 5 M STORE $end
$var reg 4 N alu_ops [3:0] $end
$var reg 3 O branch_type [2:0] $end
$var reg 32 P imm [31:0] $end
$var reg 1 4 is_branch $end
$var reg 1 3 is_i_type $end
$var reg 1 2 is_jalr $end
$var reg 1 1 is_jump $end
$var reg 1 0 is_lui $end
$var reg 1 / mem_read $end
$var reg 2 Q mem_width [1:0] $end
$var reg 1 - mem_write $end
$var reg 1 ) reg_write $end
$var reg 1 R rs1_used $end
$var reg 1 S rs2_used $end
$upscope $end
$scope module instr_mem $end
$var wire 32 T addr [31:0] $end
$var reg 1 U continue_reading $end
$var reg 32 V instr_out [31:0] $end
$var integer 32 W file [31:0] $end
$var integer 32 X i [31:0] $end
$var integer 32 Y status [31:0] $end
$upscope $end
$scope module pc_inst $end
$var wire 32 Z addr [31:0] $end
$var wire 1 ! clk $end
$var wire 1 # enable $end
$var wire 1 $ load $end
$var wire 1 9 rst $end
$var reg 32 [ pc [31:0] $end
$upscope $end
$scope module regfile_inst $end
$var wire 1 ! clk $end
$var wire 5 \ rd_addr [4:0] $end
$var wire 32 ] rd_data [31:0] $end
$var wire 5 ^ rs1_addr [4:0] $end
$var wire 5 _ rs2_addr [4:0] $end
$var wire 1 ` rst_n $end
$var wire 1 ) we $end
$var wire 32 a rs2_data [31:0] $end
$var wire 32 b rs1_data [31:0] $end
$scope begin $unm_blk_29 $end
$var integer 32 c i [31:0] $end
$upscope $end
$upscope $end
$upscope $end
$upscope $end
$enddefinitions $end
$comment Show the parameter values. $end
$dumpall
b1000 M
b1100 L
b1101 K
b0 J
b11001 I
b11011 H
b100 G
b11000 F
$end
#0
$dumpvars
bx c
b0 b
b0 a
z`
b0 _
b0 ^
b0 ]
b101 \
b0 [
b0 Z
b11111111111111111111111111111111 Y
b1011 X
b10000000000000000000000000000011 W
b1010110111 V
0U
b0 T
xS
xR
bx Q
b0 P
bx O
bx N
b0 E
b0 D
b1010110111 C
b1101 B
b101 A
b0 @
b0 ?
b0 >
bx =
b0 <
b0 ;
b0 :
19
bx 8
bx 7
b0 6
b1010110111 5
x4
03
x2
x1
10
x/
bx .
x-
b0 ,
b101 +
b0 *
1)
b0 (
b0 '
b0 &
b0 %
0$
1#
b0 "
0!
$end
#1
1!
#2
0!
#3
1!
#4
0!
#5
1!
#6
0!
#7
1!
#8
0!
#9
1!
#10
0!
09
#11
bx %
bx :
bx a
13
b0 8
b0 =
b0 N
b10 *
b10 >
b10 ]
b10 &
b10 ?
b10 _
b101 (
b101 @
b101 ^
b100 B
b10 6
b10 <
b10 P
00
b1000101000001010010011 5
b1000101000001010010011 C
b1000101000001010010011 V
b100 ,
b100 T
b100 [
1!
#12
0!
#13
b0 %
b0 :
b0 a
b0 6
b0 <
b0 P
10
b110 +
b110 A
b110 \
b0 &
b0 ?
b0 _
b0 (
b0 @
b0 ^
b1101 B
03
b0 *
b0 >
b0 ]
b1100110111 5
b1100110111 C
b1100110111 V
b0 '
b0 ;
b0 b
b1000 ,
b1000 T
b1000 [
1!
#14
0!
#15
bx %
bx :
bx a
13
b10 *
b10 >
b10 ]
b10 &
b10 ?
b10 _
b110 (
b110 @
b110 ^
b100 B
b10 6
b10 <
b10 P
00
b1000110000001100010011 5
b1000110000001100010011 C
b1000110000001100010011 V
b1100 ,
b1100 T
b1100 [
1!
#16
0!
#17
b10 %
b10 :
b10 a
1S
1R
b1010 +
b1010 A
b1010 \
b110 &
b110 ?
b110 _
b101 (
b101 @
b101 ^
b1100 B
03
b100 *
b100 >
b100 ]
b11000101000010100110011 5
b11000101000010100110011 C
b11000101000010100110011 V
b10 '
b10 ;
b10 b
b10000 ,
b10000 T
b10000 [
1!
#18
0!
#19
b0 *
b0 >
b0 ]
b0 %
b0 :
b0 a
b0 '
b0 ;
b0 b
b0 6
b0 <
b0 P
10
b101 +
b101 A
b101 \
b0 &
b0 ?
b0 _
b0 (
b0 @
b0 ^
b1101 B
b1010110111 5
b1010110111 C
b1010110111 V
b10100 ,
b10100 T
b10100 [
1!
#20
0!
#21
bx %
bx :
bx a
13
b100 *
b100 >
b100 ]
b100 &
b100 ?
b100 _
b101 (
b101 @
b101 ^
b100 B
b100 6
b100 <
b100 P
00
b10000101000001010010011 5
b10000101000001010010011 C
b10000101000001010010011 V
b11000 ,
b11000 T
b11000 [
1!
#22
0!
#23
b0 %
b0 :
b0 a
b0 6
b0 <
b0 P
10
b110 +
b110 A
b110 \
b0 &
b0 ?
b0 _
b0 (
b0 @
b0 ^
b1101 B
03
b0 *
b0 >
b0 ]
b1100110111 5
b1100110111 C
b1100110111 V
b0 '
b0 ;
b0 b
b11100 ,
b11100 T
b11100 [
1!
#24
0!
#25
bx %
bx :
bx a
13
b1 *
b1 >
b1 ]
b1 &
b1 ?
b1 _
b110 (
b110 @
b110 ^
b100 B
b1 6
b1 <
b1 P
00
b100110000001100010011 5
b100110000001100010011 C
b100110000001100010011 V
b100000 ,
b100000 T
b100000 [
1!
#26
0!
#27
b1 %
b1 :
b1 a
b1 8
b1 =
b1 N
b1010 +
b1010 A
b1010 \
b110 &
b110 ?
b110 _
b101 (
b101 @
b101 ^
b100000 D
b1100 B
03
b11 *
b11 >
b11 ]
b1000000011000101000010100110011 5
b1000000011000101000010100110011 C
b1000000011000101000010100110011 V
b100 '
b100 ;
b100 b
b100100 ,
b100100 T
b100100 [
1!
#28
0!
#29
b0 *
b0 >
b0 ]
b11 %
b11 :
b11 a
b11 '
b11 ;
b11 b
b1010 &
b1010 ?
b1010 _
b1010 (
b1010 @
b1010 ^
b1000000101001010000010100110011 5
b1000000101001010000010100110011 C
b1000000101001010000010100110011 V
b101000 ,
b101000 T
b101000 [
1!
#30
0!
#31
b0 +
b0 A
b0 \
b0 &
b0 ?
b0 _
b0 (
b0 @
b0 ^
b0 D
b0 B
b0 5
b0 C
b0 V
b0 '
b0 ;
b0 b
b0 %
b0 :
b0 a
b101100 ,
b101100 T
b101100 [
1!
#32
0!
#33
b110000 ,
b110000 T
b110000 [
1!
#34
0!
#35
b110100 ,
b110100 T
b110100 [
1!
#36
0!
#37
b111000 ,
b111000 T
b111000 [
1!
#38
0!
#39
b111100 ,
b111100 T
b111100 [
1!
#40
0!
#41
b1000000 ,
b1000000 T
b1000000 [
1!
#42
0!
#43
b1000100 ,
b1000100 T
b1000100 [
1!
#44
0!
#45
b1001000 ,
b1001000 T
b1001000 [
1!
#46
0!
#47
b1001100 ,
b1001100 T
b1001100 [
1!
#48
0!
#49
b1010000 ,
b1010000 T
b1010000 [
1!
#50
0!
#51
b1010100 ,
b1010100 T
b1010100 [
1!
#52
0!
#53
b1011000 ,
b1011000 T
b1011000 [
1!
#54
0!
#55
b1011100 ,
b1011100 T
b1011100 [
1!
#56
0!
#57
b1100000 ,
b1100000 T
b1100000 [
1!
#58
0!
#59
b1100100 ,
b1100100 T
b1100100 [
1!
#60
0!
#61
b1101000 ,
b1101000 T
b1101000 [
1!
#62
0!
#63
b1101100 ,
b1101100 T
b1101100 [
1!
#64
0!
#65
b1110000 ,
b1110000 T
b1110000 [
1!
